utils4algo/__init__.py
utils4algo/utils.py
utils4algo-0.2.0.dist-info/LICENSE
utils4algo-0.2.0.dist-info/METADATA
utils4algo-0.2.0.dist-info/WHEEL
utils4algo-0.2.0.dist-info/top_level.txt
utils4algo-0.2.0.dist-info/RECORD
