Metadata-Version: 2.1
Name: utils4algo
Version: 0.2.0
Summary: Utility functions
Home-page: https://github.com/akhilpakkath/utils
Author: Akhil Pakkath
Author-email: akhil.pakkath@gmail.com
License: UNKNOWN
Project-URL: Bug Tracker, https://github.com/pypa/sampleproject/issues
Platform: UNKNOWN
Classifier: Programming Language :: Python :: 3
Classifier: License :: OSI Approved :: MIT License
Classifier: Operating System :: OS Independent
Requires-Python: >=3.6
License-File: LICENSE
